dj_rest_kit/__init__.py
dj_rest_kit/admin.py
dj_rest_kit/constants.py
dj_rest_kit/filters.py
dj_rest_kit/helpers.py
dj_rest_kit/middleware.py
dj_rest_kit/mixins.py
dj_rest_kit/models.py
dj_rest_kit/pagination.py
dj_rest_kit/renderer.py
dj_rest_kit/serializers.py
dj_rest_kit/setup.py
dj_rest_kit/validators.py
dj_rest_kit/views.py
dj_rest_kit-1.1.1.dist-info/LICENSE
dj_rest_kit-1.1.1.dist-info/METADATA
dj_rest_kit-1.1.1.dist-info/WHEEL
dj_rest_kit-1.1.1.dist-info/top_level.txt
dj_rest_kit-1.1.1.dist-info/RECORD
